<annotation>
	<folder>images</folder>
	<filename>crushed_013.jpeg</filename>
	<path>D:\images\crushed_013.jpeg</path>
	<source>
		<database>Unknown</database>
	</source>
	<size>
		<width>257</width>
		<height>196</height>
		<depth>3</depth>
	</size>
	<segmented>0</segmented>
	<object>
		<name>plastic</name>
		<pose>Unspecified</pose>
		<truncated>0</truncated>
		<difficult>0</difficult>
		<bndbox>
			<xmin>54</xmin>
			<ymin>34</ymin>
			<xmax>208</xmax>
			<ymax>149</ymax>
		</bndbox>
	</object>
	<object>
		<name>bottle</name>
		<pose>Unspecified</pose>
		<truncated>0</truncated>
		<difficult>0</difficult>
		<bndbox>
			<xmin>53</xmin>
			<ymin>36</ymin>
			<xmax>208</xmax>
			<ymax>149</ymax>
		</bndbox>
	</object>
</annotation>
